riyapycounts/__init__.py
riyapycounts/plotting.py
riyapycounts/riyapycounts.py
riyapycounts-0.1.0.dist-info/LICENSE
riyapycounts-0.1.0.dist-info/METADATA
riyapycounts-0.1.0.dist-info/WHEEL
riyapycounts-0.1.0.dist-info/RECORD
